ocr/__init__.py
ocr/ocr_license.py
ocr_license-0.0.16.dist-info/LICENSE
ocr_license-0.0.16.dist-info/METADATA
ocr_license-0.0.16.dist-info/WHEEL
ocr_license-0.0.16.dist-info/top_level.txt
ocr_license-0.0.16.dist-info/RECORD
