Metadata-Version: 2.1
Name: ocr-license
Version: 0.0.16
Summary: A small example package
Home-page: https://github.com/pypa/sampleproject
Author: Cuong Cao
Author-email: cuong091200@gmail.com
Project-URL: Bug Tracker, https://github.com/pypa/sampleproject/issues
Classifier: Programming Language :: Python :: 3
Classifier: License :: OSI Approved :: MIT License
Classifier: Operating System :: OS Independent
Requires-Python: >=3.7
License-File: LICENSE
Requires-Dist: opencv-python-headless (==4.5.5.64)
Requires-Dist: paddleocr (==2.6.1.1)
Requires-Dist: paddlepaddle (==2.3.2)
